memegen.py
memegen-0.0.3.dist-info/top_level.txt
memegen-0.0.3.dist-info/DESCRIPTION.rst
memegen-0.0.3.dist-info/RECORD
memegen-0.0.3.dist-info/METADATA
memegen-0.0.3.dist-info/WHEEL
memegen-0.0.3.dist-info/metadata.json
memegen-0.0.3.data/scripts/memegen.py
