Metadata-Version: 2.0
Name: memegen
Version: 0.0.3
Summary: Caption images, from command line, using ImgFlip or MemeGenerator APIs.
Home-page: https://github.com/surrealcristian/memegen
Author: Cristian Cabrera
Author-email: surrealcristian@gmail.com
License: MIT
Keywords: caption images memes cli terminal command line imgflip memegenerator service api
Platform: UNKNOWN
Classifier: Development Status :: 3 - Alpha
Classifier: Environment :: Console
Classifier: Intended Audience :: Developers
Classifier: Intended Audience :: End Users/Desktop
Classifier: License :: OSI Approved :: MIT License
Classifier: Natural Language :: English
Classifier: Operating System :: POSIX
Classifier: Programming Language :: Python
Classifier: Programming Language :: Python :: 3 :: Only
Classifier: Topic :: Software Development :: Libraries
Classifier: Topic :: Games/Entertainment
Classifier: Topic :: Utilities
Requires-Dist: requests (>=2)
